{"parse": {"title": "Erika", "pageid": 1115, "redirects": [{"from": "Erika (anime)", "to": "Erika", "tofragment": "In animation"}], "sections": [{"toclevel": 1, "level": "2", "line": "Appearance", "number": "1", "index": "1", "fromtitle": "Erika", "byteoffset": 3456, "anchor": "Appearance", "linkAnchor": "Appearance"}, {"toclevel": 2, "level": "4", "line": "Pok\u00e9mon Red, Blue, and Yellow", "number": "1.1", "index": "2", "fromtitle": "Erika", "byteoffset": 3644, "anchor": "Pok\u00e9mon_Red,_Blue,_and_Yellow", "linkAnchor": "Pok\u00e9mon_Red,_Blue,_and_Yellow"}, {"toclevel": 2, "level": "4", "line": "Pok\u00e9mon FireRed and LeafGreen", "number": "1.2", "index": "3", "fromtitle": "Erika", "byteoffset": 3795, "anchor": "Pok\u00e9mon_FireRed_and_LeafGreen", "linkAnchor": "Pok\u00e9mon_FireRed_and_LeafGreen"}, {"toclevel": 2, "level": "4", "line": "Pok\u00e9mon HeartGold and SoulSilver", "number": "1.3", "index": "4", "fromtitle": "Erika", "byteoffset": 4031, "anchor": "Pok\u00e9mon_HeartGold_and_SoulSilver", "linkAnchor": "Pok\u00e9mon_HeartGold_and_SoulSilver"}, {"toclevel": 2, "level": "4", "line": "Pok\u00e9mon: Let's Go, Pikachu! and Let's Go, Eevee!", "number": "1.4", "index": "5", "fromtitle": "Erika", "byteoffset": 4228, "anchor": "Pok\u00e9mon:_Let's_Go,_Pikachu!_and_Let's_Go,_Eevee!", "linkAnchor": "Pok\u00e9mon:_Let's_Go,_Pikachu!_and_Let's_Go,_Eevee!"}, {"toclevel": 1, "level": "2", "line": "In the core series games", "number": "2", "index": "6", "fromtitle": "Erika", "byteoffset": 4508, "anchor": "In_the_core_series_games", "linkAnchor": "In_the_core_series_games"}, {"toclevel": 2, "level": "3", "line": "Fame Checker", "number": "2.1", "index": "7", "fromtitle": "Erika", "byteoffset": 5844, "anchor": "Fame_Checker", "linkAnchor": "Fame_Checker"}, {"toclevel": 2, "level": "3", "line": "Pok\u00e9mon", "number": "2.2", "index": "8", "fromtitle": "Erika", "byteoffset": 7234, "anchor": "Pok\u00e9mon", "linkAnchor": "Pok\u00e9mon"}, {"toclevel": 3, "level": "4", "line": "Pok\u00e9mon Red and Blue", "number": "2.2.1", "index": "9", "fromtitle": "Erika", "byteoffset": 7248, "anchor": "Pok\u00e9mon_Red_and_Blue", "linkAnchor": "Pok\u00e9mon_Red_and_Blue"}, {"toclevel": 3, "level": "4", "line": "Pok\u00e9mon Yellow", "number": "2.2.2", "index": "10", "fromtitle": "Erika", "byteoffset": 8358, "anchor": "Pok\u00e9mon_Yellow", "linkAnchor": "Pok\u00e9mon_Yellow"}, {"toclevel": 3, "level": "4", "line": "Pok\u00e9mon Gold, Silver, and Crystal", "number": "2.2.3", "index": "11", "fromtitle": "Erika", "byteoffset": 9523, "anchor": "Pok\u00e9mon_Gold,_Silver,_and_Crystal", "linkAnchor": "Pok\u00e9mon_Gold,_Silver,_and_Crystal"}, {"toclevel": 3, "level": "4", "line": "Pok\u00e9mon FireRed and LeafGreen", "number": "2.2.4", "index": "12", "fromtitle": "Erika", "byteoffset": 10977, "anchor": "Pok\u00e9mon_FireRed_and_LeafGreen_2", "linkAnchor": "Pok\u00e9mon_FireRed_and_LeafGreen_2"}, {"toclevel": 3, "level": "4", "line": "Pok\u00e9mon HeartGold and SoulSilver", "number": "2.2.5", "index": "13", "fromtitle": "Erika", "byteoffset": 12268, "anchor": "Pok\u00e9mon_HeartGold_and_SoulSilver_2", "linkAnchor": "Pok\u00e9mon_HeartGold_and_SoulSilver_2"}, {"toclevel": 4, "level": "5", "line": "Gym battle", "number": "2.2.5.1", "index": "14", "fromtitle": "Erika", "byteoffset": 12312, "anchor": "Gym_battle", "linkAnchor": "Gym_battle"}, {"toclevel": 4, "level": "5", "line": "Rematch", "number": "2.2.5.2", "index": "15", "fromtitle": "Erika", "byteoffset": 14207, "anchor": "Rematch", "linkAnchor": "Rematch"}, {"toclevel": 3, "level": "4", "line": "Pok\u00e9mon Black 2 and White 2", "number": "2.2.6", "index": "16", "fromtitle": "Erika", "byteoffset": 16912, "anchor": "Pok\u00e9mon_Black_2_and_White_2", "linkAnchor": "Pok\u00e9mon_Black_2_and_White_2"}, {"toclevel": 4, "level": "5", "line": "Pok\u00e9mon World Tournament", "number": "2.2.6.1", "index": "17", "fromtitle": "Erika", "byteoffset": 16929, "anchor": "Pok\u00e9mon_World_Tournament", "linkAnchor": "Pok\u00e9mon_World_Tournament"}, {"toclevel": 5, "level": "6", "line": "Kanto Leaders Tournament", "number": "2.2.6.1.1", "index": "18", "fromtitle": "Erika", "byteoffset": 17203, "anchor": "Kanto_Leaders_Tournament", "linkAnchor": "Kanto_Leaders_Tournament"}, {"toclevel": 5, "level": "6", "line": "Type Expert/World Leaders Tournament", "number": "2.2.6.1.2", "index": "19", "fromtitle": "Erika", "byteoffset": 20058, "anchor": "Type_Expert/World_Leaders_Tournament", "linkAnchor": "Type_Expert/World_Leaders_Tournament"}, {"toclevel": 5, "level": "6", "line": "Challenge the Champion Lance!", "number": "2.2.6.1.3", "index": "20", "fromtitle": "Erika", "byteoffset": 22947, "anchor": "Challenge_the_Champion_Lance!", "linkAnchor": "Challenge_the_Champion_Lance!"}, {"toclevel": 3, "level": "4", "line": "Pok\u00e9mon: Let's Go, Pikachu! and Let's Go, Eevee!", "number": "2.2.7", "index": "21", "fromtitle": "Erika", "byteoffset": 24522, "anchor": "Pok\u00e9mon:_Let's_Go,_Pikachu!_and_Let's_Go,_Eevee!_2", "linkAnchor": "Pok\u00e9mon:_Let's_Go,_Pikachu!_and_Let's_Go,_Eevee!_2"}, {"toclevel": 4, "level": "5", "line": "Gym battle", "number": "2.2.7.1", "index": "22", "fromtitle": "Erika", "byteoffset": 24583, "anchor": "Gym_battle_2", "linkAnchor": "Gym_battle_2"}, {"toclevel": 4, "level": "5", "line": "Rematch", "number": "2.2.7.2", "index": "23", "fromtitle": "Erika", "byteoffset": 25668, "anchor": "Rematch_2", "linkAnchor": "Rematch_2"}, {"toclevel": 1, "level": "2", "line": "In the side series games", "number": "3", "index": "24", "fromtitle": "Erika", "byteoffset": 27813, "anchor": "In_the_side_series_games", "linkAnchor": "In_the_side_series_games"}, {"toclevel": 2, "level": "3", "line": "Pok\u00e9mon Stadium", "number": "3.1", "index": "25", "fromtitle": "Erika", "byteoffset": 27842, "anchor": "Pok\u00e9mon_Stadium", "linkAnchor": "Pok\u00e9mon_Stadium"}, {"toclevel": 3, "level": "4", "line": "Pok\u00e9mon", "number": "3.1.1", "index": "26", "fromtitle": "Erika", "byteoffset": 28058, "anchor": "Pok\u00e9mon_2", "linkAnchor": "Pok\u00e9mon_2"}, {"toclevel": 4, "level": "5", "line": "Round 1", "number": "3.1.1.1", "index": "27", "fromtitle": "Erika", "byteoffset": 28074, "anchor": "Round_1", "linkAnchor": "Round_1"}, {"toclevel": 4, "level": "5", "line": "Round 2", "number": "3.1.1.2", "index": "28", "fromtitle": "Erika", "byteoffset": 29949, "anchor": "Round_2", "linkAnchor": "Round_2"}, {"toclevel": 2, "level": "3", "line": "Pok\u00e9mon Stadium 2", "number": "3.2", "index": "29", "fromtitle": "Erika", "byteoffset": 31808, "anchor": "Pok\u00e9mon_Stadium_2", "linkAnchor": "Pok\u00e9mon_Stadium_2"}, {"toclevel": 3, "level": "4", "line": "Pok\u00e9mon", "number": "3.2.1", "index": "30", "fromtitle": "Erika", "byteoffset": 32155, "anchor": "Pok\u00e9mon_3", "linkAnchor": "Pok\u00e9mon_3"}, {"toclevel": 4, "level": "5", "line": "Round 1", "number": "3.2.1.1", "index": "31", "fromtitle": "Erika", "byteoffset": 32171, "anchor": "Round_1_2", "linkAnchor": "Round_1_2"}, {"toclevel": 4, "level": "5", "line": "Round 2", "number": "3.2.1.2", "index": "32", "fromtitle": "Erika", "byteoffset": 34245, "anchor": "Round_2_2", "linkAnchor": "Round_2_2"}, {"toclevel": 1, "level": "2", "line": "In the spin-off games", "number": "4", "index": "33", "fromtitle": "Erika", "byteoffset": 36354, "anchor": "In_the_spin-off_games", "linkAnchor": "In_the_spin-off_games"}, {"toclevel": 2, "level": "3", "line": "Pok\u00e9mon Puzzle League", "number": "4.1", "index": "34", "fromtitle": "Erika", "byteoffset": 36479, "anchor": "Pok\u00e9mon_Puzzle_League", "linkAnchor": "Pok\u00e9mon_Puzzle_League"}, {"toclevel": 3, "level": "4", "line": "Pok\u00e9mon", "number": "4.1.1", "index": "35", "fromtitle": "Erika", "byteoffset": 36693, "anchor": "Pok\u00e9mon_4", "linkAnchor": "Pok\u00e9mon_4"}, {"toclevel": 2, "level": "3", "line": "Pok\u00e9mon Masters EX", "number": "4.2", "index": "36", "fromtitle": "Erika", "byteoffset": 36987, "anchor": "Pok\u00e9mon_Masters_EX", "linkAnchor": "Pok\u00e9mon_Masters_EX"}, {"toclevel": 2, "level": "3", "line": "Pok\u00e9mon Trading Card Game Pocket", "number": "4.3", "index": "37", "fromtitle": "Erika", "byteoffset": 38533, "anchor": "Pok\u00e9mon_Trading_Card_Game_Pocket", "linkAnchor": "Pok\u00e9mon_Trading_Card_Game_Pocket"}, {"toclevel": 1, "level": "2", "line": "Gallery", "number": "5", "index": "38", "fromtitle": "Erika", "byteoffset": 39246, "anchor": "Gallery", "linkAnchor": "Gallery"}, {"toclevel": 2, "level": "3", "line": "Artwork", "number": "5.1", "index": "39", "fromtitle": "Erika", "byteoffset": 39258, "anchor": "Artwork", "linkAnchor": "Artwork"}, {"toclevel": 2, "level": "3", "line": "Sprites and models", "number": "5.2", "index": "40", "fromtitle": "Erika", "byteoffset": 41684, "anchor": "Sprites_and_models", "linkAnchor": "Sprites_and_models"}, {"toclevel": 3, "level": "4", "line": "In the core series", "number": "5.2.1", "index": "41", "fromtitle": "Erika", "byteoffset": 41709, "anchor": "In_the_core_series", "linkAnchor": "In_the_core_series"}, {"toclevel": 3, "level": "4", "line": "In other games", "number": "5.2.2", "index": "42", "fromtitle": "Erika", "byteoffset": 45109, "anchor": "In_other_games", "linkAnchor": "In_other_games"}, {"toclevel": 1, "level": "2", "line": "Quotes", "number": "6", "index": "43", "fromtitle": "Erika", "byteoffset": 46011, "anchor": "Quotes", "linkAnchor": "Quotes"}, {"toclevel": 1, "level": "2", "line": "In animation", "number": "7", "index": "44", "fromtitle": "Erika", "byteoffset": 46045, "anchor": "In_animation", "linkAnchor": "In_animation"}, {"toclevel": 2, "level": "3", "line": "<i>Pok\u00e9mon the Series</i>", "number": "7.1", "index": "45", "fromtitle": "Erika", "byteoffset": 46062, "anchor": "Pok\u00e9mon_the_Series", "linkAnchor": "Pok\u00e9mon_the_Series"}, {"toclevel": 3, "level": "4", "line": "History", "number": "7.1.1", "index": "46", "fromtitle": "Erika", "byteoffset": 46219, "anchor": "History", "linkAnchor": "History"}, {"toclevel": 4, "level": "5", "line": "Pre-series", "number": "7.1.1.1", "index": "47", "fromtitle": "Erika", "byteoffset": 46235, "anchor": "Pre-series", "linkAnchor": "Pre-series"}, {"toclevel": 4, "level": "5", "line": "<i>Pok\u00e9mon the Series: The Beginning</i>", "number": "7.1.1.2", "index": "48", "fromtitle": "Erika", "byteoffset": 46591, "anchor": "Pok\u00e9mon_the_Series:_The_Beginning", "linkAnchor": "Pok\u00e9mon_the_Series:_The_Beginning"}, {"toclevel": 4, "level": "5", "line": "<i>Pok\u00e9mon the Series: Gold and Silver</i>", "number": "7.1.1.3", "index": "49", "fromtitle": "Erika", "byteoffset": 48402, "anchor": "Pok\u00e9mon_the_Series:_Gold_and_Silver", "linkAnchor": "Pok\u00e9mon_the_Series:_Gold_and_Silver"}, {"toclevel": 4, "level": "5", "line": "<i>Pok\u00e9mon Journeys: The Series</i>", "number": "7.1.1.4", "index": "50", "fromtitle": "Erika", "byteoffset": 48524, "anchor": "Pok\u00e9mon_Journeys:_The_Series", "linkAnchor": "Pok\u00e9mon_Journeys:_The_Series"}, {"toclevel": 3, "level": "4", "line": "Character", "number": "7.1.2", "index": "51", "fromtitle": "Erika", "byteoffset": 49250, "anchor": "Character", "linkAnchor": "Character"}, {"toclevel": 3, "level": "4", "line": "Pok\u00e9mon", "number": "7.1.3", "index": "52", "fromtitle": "Erika", "byteoffset": 49837, "anchor": "Pok\u00e9mon_5", "linkAnchor": "Pok\u00e9mon_5"}, {"toclevel": 4, "level": "5", "line": "On hand", "number": "7.1.3.1", "index": "53", "fromtitle": "Erika", "byteoffset": 49881, "anchor": "On_hand", "linkAnchor": "On_hand"}, {"toclevel": 4, "level": "5", "line": "At the Celadon Gym", "number": "7.1.3.2", "index": "54", "fromtitle": "Erika", "byteoffset": 52920, "anchor": "At_the_Celadon_Gym", "linkAnchor": "At_the_Celadon_Gym"}, {"toclevel": 3, "level": "4", "line": "Voice actors", "number": "7.1.4", "index": "55", "fromtitle": "Erika", "byteoffset": 56967, "anchor": "Voice_actors", "linkAnchor": "Voice_actors"}, {"toclevel": 2, "level": "3", "line": "<i>I Choose You!</i>", "number": "7.2", "index": "56", "fromtitle": "Erika", "byteoffset": 57875, "anchor": "I_Choose_You!", "linkAnchor": "I_Choose_You!"}, {"toclevel": 3, "level": "4", "line": "Pok\u00e9mon", "number": "7.2.1", "index": "57", "fromtitle": "Erika", "byteoffset": 58267, "anchor": "Pok\u00e9mon_6", "linkAnchor": "Pok\u00e9mon_6"}, {"toclevel": 3, "level": "4", "line": "Voice actors", "number": "7.2.2", "index": "58", "fromtitle": "Erika", "byteoffset": 58708, "anchor": "Voice_actors_2", "linkAnchor": "Voice_actors_2"}, {"toclevel": 2, "level": "3", "line": "Pok\u00e9mon Origins", "number": "7.3", "index": "59", "fromtitle": "Erika", "byteoffset": 59043, "anchor": "Pok\u00e9mon_Origins", "linkAnchor": "Pok\u00e9mon_Origins"}, {"toclevel": 3, "level": "4", "line": "Pok\u00e9mon", "number": "7.3.1", "index": "60", "fromtitle": "Erika", "byteoffset": 59407, "anchor": "Pok\u00e9mon_7", "linkAnchor": "Pok\u00e9mon_7"}, {"toclevel": 2, "level": "3", "line": "GOTCHA!", "number": "7.4", "index": "61", "fromtitle": "Erika", "byteoffset": 59794, "anchor": "GOTCHA!", "linkAnchor": "GOTCHA!"}, {"toclevel": 1, "level": "2", "line": "In the manga", "number": "8", "index": "62", "fromtitle": "Erika", "byteoffset": 59848, "anchor": "In_the_manga", "linkAnchor": "In_the_manga"}, {"toclevel": 2, "level": "3", "line": "Pok\u00e9mon Adventures", "number": "8.1", "index": "63", "fromtitle": "Erika", "byteoffset": 59865, "anchor": "Pok\u00e9mon_Adventures", "linkAnchor": "Pok\u00e9mon_Adventures"}, {"toclevel": 3, "level": "4", "line": "History", "number": "8.1.1", "index": "64", "fromtitle": "Erika", "byteoffset": 60018, "anchor": "History_2", "linkAnchor": "History_2"}, {"toclevel": 4, "level": "5", "line": "<i>Red, Green &amp; Blue</i> arc", "number": "8.1.1.1", "index": "65", "fromtitle": "Erika", "byteoffset": 60034, "anchor": "Red,_Green_&_Blue_arc", "linkAnchor": "Red,_Green_&_Blue_arc"}, {"toclevel": 4, "level": "5", "line": "<i>Yellow</i> arc", "number": "8.1.1.2", "index": "66", "fromtitle": "Erika", "byteoffset": 60551, "anchor": "Yellow_arc", "linkAnchor": "Yellow_arc"}, {"toclevel": 4, "level": "5", "line": "<i>Gold, Silver &amp; Crystal</i> arc", "number": "8.1.1.3", "index": "67", "fromtitle": "Erika", "byteoffset": 61840, "anchor": "Gold,_Silver_&_Crystal_arc", "linkAnchor": "Gold,_Silver_&_Crystal_arc"}, {"toclevel": 3, "level": "4", "line": "Character", "number": "8.1.2", "index": "68", "fromtitle": "Erika", "byteoffset": 62497, "anchor": "Character_2", "linkAnchor": "Character_2"}, {"toclevel": 3, "level": "4", "line": "Pok\u00e9mon", "number": "8.1.3", "index": "69", "fromtitle": "Erika", "byteoffset": 62765, "anchor": "Pok\u00e9mon_8", "linkAnchor": "Pok\u00e9mon_8"}, {"toclevel": 2, "level": "3", "line": "Pok\u00e9mon Pocket Monsters", "number": "8.2", "index": "70", "fromtitle": "Erika", "byteoffset": 65895, "anchor": "Pok\u00e9mon_Pocket_Monsters", "linkAnchor": "Pok\u00e9mon_Pocket_Monsters"}, {"toclevel": 3, "level": "4", "line": "Pok\u00e9mon", "number": "8.2.1", "index": "71", "fromtitle": "Erika", "byteoffset": 66682, "anchor": "Pok\u00e9mon_9", "linkAnchor": "Pok\u00e9mon_9"}, {"toclevel": 4, "level": "5", "line": "On hand", "number": "8.2.1.1", "index": "72", "fromtitle": "Erika", "byteoffset": 66698, "anchor": "On_hand_2", "linkAnchor": "On_hand_2"}, {"toclevel": 4, "level": "5", "line": "Status unknown", "number": "8.2.1.2", "index": "73", "fromtitle": "Erika", "byteoffset": 67938, "anchor": "Status_unknown", "linkAnchor": "Status_unknown"}, {"toclevel": 4, "level": "5", "line": "Stolen from her father", "number": "8.2.1.3", "index": "74", "fromtitle": "Erika", "byteoffset": 68572, "anchor": "Stolen_from_her_father", "linkAnchor": "Stolen_from_her_father"}, {"toclevel": 2, "level": "3", "line": "Pok\u00e9mon Zensho", "number": "8.3", "index": "75", "fromtitle": "Erika", "byteoffset": 69033, "anchor": "Pok\u00e9mon_Zensho", "linkAnchor": "Pok\u00e9mon_Zensho"}, {"toclevel": 3, "level": "4", "line": "Pok\u00e9mon", "number": "8.3.1", "index": "76", "fromtitle": "Erika", "byteoffset": 69441, "anchor": "Pok\u00e9mon_10", "linkAnchor": "Pok\u00e9mon_10"}, {"toclevel": 4, "level": "5", "line": "On hand", "number": "8.3.1.1", "index": "77", "fromtitle": "Erika", "byteoffset": 69457, "anchor": "On_hand_3", "linkAnchor": "On_hand_3"}, {"toclevel": 4, "level": "5", "line": "In the Gym", "number": "8.3.1.2", "index": "78", "fromtitle": "Erika", "byteoffset": 69859, "anchor": "In_the_Gym", "linkAnchor": "In_the_Gym"}, {"toclevel": 2, "level": "3", "line": "How I Became a Pok\u00e9mon Card", "number": "8.4", "index": "79", "fromtitle": "Erika", "byteoffset": 70153, "anchor": "How_I_Became_a_Pok\u00e9mon_Card", "linkAnchor": "How_I_Became_a_Pok\u00e9mon_Card"}, {"toclevel": 2, "level": "3", "line": "Pocket Monsters HGSS J\u014d's Big Adventure", "number": "8.5", "index": "80", "fromtitle": "Erika", "byteoffset": 71067, "anchor": "Pocket_Monsters_HGSS_J\u014d's_Big_Adventure", "linkAnchor": "Pocket_Monsters_HGSS_J\u014d's_Big_Adventure"}, {"toclevel": 1, "level": "2", "line": "In the TCG", "number": "9", "index": "81", "fromtitle": "Erika", "byteoffset": 71298, "anchor": "In_the_TCG", "linkAnchor": "In_the_TCG"}, {"toclevel": 2, "level": "3", "line": "Artwork", "number": "9.1", "index": "82", "fromtitle": "Erika", "byteoffset": 72560, "anchor": "Artwork_2", "linkAnchor": "Artwork_2"}, {"toclevel": 2, "level": "3", "line": "Cards", "number": "9.2", "index": "83", "fromtitle": "Erika", "byteoffset": 74288, "anchor": "Cards", "linkAnchor": "Cards"}, {"toclevel": 1, "level": "2", "line": "In the TFG", "number": "10", "index": "84", "fromtitle": "Erika", "byteoffset": 88121, "anchor": "In_the_TFG", "linkAnchor": "In_the_TFG"}, {"toclevel": 1, "level": "2", "line": "Trivia", "number": "11", "index": "85", "fromtitle": "Erika", "byteoffset": 88302, "anchor": "Trivia", "linkAnchor": "Trivia"}, {"toclevel": 1, "level": "2", "line": "Names", "number": "12", "index": "86", "fromtitle": "Erika", "byteoffset": 90361, "anchor": "Names", "linkAnchor": "Names"}, {"toclevel": 2, "level": "3", "line": "Erika's Pok\u00e9mon", "number": "12.1", "index": "87", "fromtitle": "Erika", "byteoffset": 92125, "anchor": "Erika's_Pok\u00e9mon", "linkAnchor": "Erika's_Pok\u00e9mon"}, {"toclevel": 2, "level": "3", "line": "Notes", "number": "12.2", "index": "88", "fromtitle": "Erika", "byteoffset": 92834, "anchor": "Notes", "linkAnchor": "Notes"}, {"toclevel": 1, "level": "2", "line": "References", "number": "13", "index": "89", "fromtitle": "Erika", "byteoffset": 92867, "anchor": "References", "linkAnchor": "References"}], "showtoc": ""}}