{"parse": {"title": "Blaine", "pageid": 2325, "redirects": [], "wikitext": {"*": "===[[Pok\u00e9mon Masters EX]]===\n{{main|Blaine (Masters)}}\nBlaine, in his {{game|FireRed and LeafGreen|s}} design, forms a [[sync pair]] with {{p|Ponyta}} and its evolved form {{p|Rapidash}} in [[Pok\u00e9mon Masters EX]]. Blaine became a playable sync pair since the game's release.\n\n{{PairDex/h|Fire}}\n{{PairDex|006|Blaine|trainerlink=Blaine (Masters)#Ponyta \u2192 Rapidash|trainerimg=Blaine|0078|Ponyta \u2192 Rapidash|pokemonlink=Ponyta (Pok\u00e9mon)|gender=male|Fire|Rock|Tech|4EX|Sync Pair Scout}}\n|}"}}}