{"parse": {"title": "Byron", "pageid": 13652, "redirects": [], "wikitext": {"*": "===={{game|Diamond and Pearl|s}}====\n{{Party\n| background = {{steel color}}\n| border = {{steel color dark}}\n| headcolor = {{steel color light}}\n| sprite = Spr DP Byron.png\n| prize = {{pdollar}}4680\n| class = Leader\n| classlink = Gym Leader\n| name = Byron\n| location = Canalave Gym\n| game = DP\n| pokemon = 3\n}}\n{{Pok\u00e9mon\n| gen = 4\n| ndex = 0436\n| pokemon = Bronzor\n| gender = none\n| level = 36\n| type1 = Steel\n| type2 = Psychic\n| ability = Levitate\n| move1 = Flash Cannon | move1type = Steel | move1cat = Special\n| move2 = Extrasensory | move2type = Psychic | move2cat = Special\n| move3 = Confuse Ray | move3type = Ghost | move3cat = Status\n| move4 = Hypnosis | move4type = Psychic | move4cat = Status\n}}\n{{Pok\u00e9mon\n| gen = 4\n| ndex = 0208\n| pokemon = Steelix\n| gender = male\n| level = 36\n| type1 = Steel\n| type2 = Ground\n| ability = Sturdy\n| move1 = Gyro Ball | move1type = Steel | move1cat = Physical\n| move2 = DragonBreath | move2type = Dragon | move2cat = Special\n| move3 = Ice Fang | move3type = Ice | move3cat = Physical\n| move4 = Sandstorm | move4type = Rock | move4cat = Status\n}}\n{{Pok\u00e9mon\n| gen = 4\n| ndex = 0411\n| pokemon = Bastiodon\n| gender = male\n| level = 39\n| type1 = Rock\n| type2 = Steel\n| ability = Sturdy\n| held = Chesto Berry\n| move1 = Flash Cannon | move1type = Steel | move1cat = Special\n| move2 = AncientPower | move2type = Rock | move2cat = Special\n| move3 = Iron Defense | move3type = Steel | move3cat = Status\n| move4 = Rest | move4type = Psychic | move4cat = Status\n}}\n{{Party/end}}"}}}