{"parse": {"title": "Brock", "pageid": 60694, "redirects": [{"from": "Brock (game)", "to": "Brock"}], "wikitext": {"*": "====Pok\u00e9mon====\n=====Round 1=====\n{{Party\n| background = {{rock color}}\n| border = {{rock color dark}}\n| headcolor = {{rock color light}}\n| sprite = Brock Stadium.png{{!}}55px\n| prize = none<!--GEN I HAD NO CLASSES-->\n| name = Brock\n| location = Gym Leader Castle\n| game = Stadium\n| pokemon = 6\n}}\n{{Pok\u00e9mon\n| gen = 1\n| ndex = 0095\n| pokemon = Onix\n| level = 50-100\n| type1 = Rock\n| type2 = Ground\n| move1 = Bind | move1type = Normal\n| move2 = Toxic | move2type = Poison\n| move3 = Earthquake | move3type = Ground\n| move4 = Rock Slide | move4type = Rock\n}}\n{{Pok\u00e9mon\n| gen = 1\n| ndex = 0075\n| pokemon = Graveler\n| level = 50-100\n| type1 = Rock\n| type2 = Ground\n| move1 = Rock Slide | move1type = Rock\n| move2 = Dig | move2type = Ground\n| move3 = Selfdestruct | move3type = Normal\n| move4 = Seismic Toss | move4type = Fighting\n}}\n{{Pok\u00e9mon\n| gen = 1\n| ndex = 0104\n| pokemon = Cubone\n| level = 50-100\n| type1 = Ground\n| move1 = Body Slam | move1type = Normal\n| move2 = Fissure | move2type = Ground\n| move3 = Bone Club | move3type = Ground\n| move4 = Submission | move4type = Fighting\n}}\n{{Pok\u00e9mon\n| gen = 1\n| ndex = 0037\n| pokemon = Vulpix\n| level = 50-100\n| type1 = Fire\n| move1 = Swift | move1type = Normal\n| move2 = Quick Attack | move2type = Normal\n| move3 = Flamethrower | move3type = Fire\n| move4 = Fire Spin | move4type = Fire\n}}\n{{Pok\u00e9mon\n| gen = 1\n| ndex = 0138\n| pokemon = Omanyte\n| level = 50-100\n| type1 = Rock\n| type2 = Water\n| move1 = Horn Attack | move1type = Normal\n| move2 = Spike Cannon | move2type = Normal\n| move3 = Ice Beam | move3type = Ice\n| move4 = Surf | move4type = Water\n}}\n{{Pok\u00e9mon\n| gen = 1\n| ndex = 0140\n| pokemon = Kabuto\n| level = 50-100\n| type1 = Rock\n| type2 = Water\n| move1 = Absorb | move1type = Grass\n| move2 = Slash | move2type = Normal\n| move3 = Hydro Pump | move3type = Water\n| move4 = Blizzard | move4type = Ice\n}}\n{{Party/end}}\n\n=====Round 2=====\n{{Party\n| background = {{rock color}}\n| border = {{rock color dark}}\n| headcolor = {{rock color light}}\n| sprite = Brock Stadium.png{{!}}55px\n| prize = none<!--GEN I HAD NO CLASSES-->\n| name = Brock\n| location = Gym Leader Castle\n| game = Stadium\n| pokemon = 6\n}}\n{{Pok\u00e9mon\n| gen = 1\n| ndex = 0095\n| pokemon = Onix\n| level = 50-100\n| type1 = Rock\n| type2 = Ground\n| move1 = Bind | move1type = Normal\n| move2 = Rock Slide | move2type = Rock\n| move3 = Earthquake | move3type = Ground\n| move4 = Screech | move4type = Normal\n}}\n{{Pok\u00e9mon\n| gen = 1\n| ndex = 0042\n| pokemon = Golbat\n| level = 50-100\n| type1 = Poison\n| type2 = Flying\n| move1 = Confuse Ray | move1type = Ghost\n| move2 = Wing Attack | move2type = Flying\n| move3 = Bide | move3type = Normal\n| move4 = Take Down | move4type = Normal\n}}\n{{Pok\u00e9mon\n| gen = 1\n| ndex = 0076\n| pokemon = Golem\n| level = 50-100\n| type1 = Rock\n| type2 = Ground\n| move1 = Rock Slide | move1type = Rock\n| move2 = Dig | move2type = Ground\n| move3 = Explosion | move3type = Normal\n| move4 = Seismic Toss | move4type = Fighting\n}}\n{{Pok\u00e9mon\n| gen = 1\n| ndex = 0038\n| pokemon = Ninetales\n| level = 50-100\n| type1 = Fire\n| move1 = Bide | move1type = Normal\n| move2 = Confuse Ray | move2type = Ghost\n| move3 = Flamethrower | move3type = Fire\n| move4 = Fire Spin | move4type = Fire\n}}\n{{Pok\u00e9mon\n| gen = 1\n| ndex = 0051\n| pokemon = Dugtrio\n| level = 50-100\n| type1 = Ground\n| move1 = Dig | move1type = Ground\n| move2 = Slash | move2type = Normal\n| move3 = Rock Slide | move3type = Rock\n| move4 = Sand-Attack | move4type = Normal\n}}\n{{Pok\u00e9mon\n| gen = 1\n| ndex = 0139\n| pokemon = Omastar\n| level = 50-100\n| type1 = Rock\n| type2 = Water\n| move1 = Double-Edge | move1type = Normal\n| move2 = Toxic | move2type = Poison\n| move3 = Ice Beam | move3type = Ice\n| move4 = Surf | move4type = Water\n}}\n{{Party/end}}"}}}