{"parse": {"title": "Brycen", "pageid": 115744, "redirects": [], "wikitext": {"*": "====''Pok\u00e9mon the Series: Black & White''====\nBrycen debuted in ''[[BW078|Guarding the Guardian of the Mountain!]]'', where he and his {{p|Beartic}} saved {{Ash}} and {{ashfr}} from a falling boulder. {{an|Cilan}} was the first to recognize him as a famous movie star who had the lead role in many movies, up until he decided to quit acting during production of another movie. He explained that he had come to the mountains for training and started to find traps set up by [[Pok\u00e9mon hunters]].\n\nAsh was interested in Brycen's training and tried to copy him and Beartic with his {{AP|Krokorok}}, without any good results. During the break in his training, he was asked why he decided to not act in movies anymore, and he explained it was because of an accident that happened onset. Nobody was hurt, but he felt that the accident wouldn't have happened if he was trained better.\n\nLater, Brycen stopped Pok\u00e9mon hunter [[Rizzo]]'s attempt to capture a {{p|Volcarona}} by defeating his two {{p|Jellicent}} with his Beartic. After [[Officer Jenny]] carted Rizzo off to jail, he found out that Ash was on his way to [[Icirrus City]] in order to battle the [[Gym Leader]]. It was then that he revealed that he was the Gym Leader of the [[Icirrus Gym]], surprising everyone.\n\nAfter making it to Icirrus City in ''[[BW079|Caution: Icy Battle Conditions!]]'', Ash faced Brycen at the Icirrus Gym. In the end, Ash's Krokorok, despite being at a type disadvantage, was able to win against Beartic and secure Ash the {{badge|Freeze}}.\n\nHe reappeared in a flashback in ''[[BW103|Curtain Up, Unova League!]]''."}}}