{"parse": {"title": "Diantha", "pageid": 182728, "redirects": [], "wikitext": {"*": "===Pok\u00e9mon===\n====[[Pok\u00e9mon X and Y]]====\nDiantha will always send out {{p|Gardevoir}} last and [[Mega Evolution|Mega Evolve]] it at the first opportunity.\n====={{kal|Pok\u00e9mon League}}=====\n{{Party\n| background = F3F7FA\n| border = BAC5D7\n| headcolor = E8E48E\n| sprite = VSDiantha.png\n| size = 150px\n| prize = {{pdollar}}16,320\n| class=Champion\n| classlink=Pok\u00e9mon Champion\n| name = Diantha\n| location = Pok\u00e9mon League (Kalos)\n| locationname = Pok\u00e9mon League\n| game = XY\n| pokemon = 6\n}}\n{{Pok\u00e9mon\n| gen = 6\n| ndex = 0701\n| pokemon = Hawlucha\n| gender = female\n| level = 64\n| type1 = Fighting\n| type2 = Flying\n| ability = Limber\n| move1 = Swords Dance | move1type = Normal | move1cat = Status\n| move2 = Flying Press | move2type = Fighting | move2cat = Physical\n| move3 = X-Scissor | move3type = Bug | move3cat = Physical\n| move4 = Poison Jab | move4type = Poison | move4cat = Physical\n}}\n{{Pok\u00e9mon\n| gen = 6\n| ndex = 0697\n| pokemon = Tyrantrum\n| gender = male\n| level = 65\n| type1 = Rock\n| type2 = Dragon\n| ability = Strong Jaw\n| move1 = Head Smash | move1type = Rock | move1cat = Physical\n| move2 = Earthquake | move2type = Ground | move2cat = Physical\n| move3 = Dragon Claw | move3type = Dragon | move3cat = Physical\n| move4 = Crunch | move4type = Dark | move4cat = Physical\n}}\n{{Pok\u00e9mon\n| gen = 6\n| ndex = 0699\n| pokemon = Aurorus\n| gender = male\n| level = 65\n| type1 = Rock\n| type2 = Ice\n| ability = Refrigerate\n| move1 = Thunder | move1type = Electric | move1cat = Special\n| move2 = Blizzard | move2type = Ice | move2cat = Special\n| move3 = Light Screen | move3type = Psychic | move3cat = Status\n| move4 = Reflect | move4type = Psychic | move4cat = Status\n}}\n{{Pok\u00e9mon\n| gen = 6\n| ndex = 0711\n| pokemon = Gourgeist\n| gender = female\n| level = 65<br>{{color2|000|List of Pok\u00e9mon with form differences#Gourgeist|Average Size}}\n| type1 = Ghost\n| type2 = Grass\n| ability = Pickup\n| move1 = Trick-or-Treat | move1type = Ghost | move1cat = Status\n| move2 = Phantom Force | move2type = Ghost | move2cat = Physical\n| move3 = Seed Bomb | move3type = Grass | move3cat = Physical\n| move4 = Shadow Sneak | move4type = Ghost | move4cat = Physical\n}}\n{{Pok\u00e9mon\n| gen = 6\n| ndex = 0706\n| pokemon = Goodra\n| gender = female\n| level = 66\n| type1 = Dragon\n| ability = Sap Sipper\n| move1 = Dragon Pulse | move1type = Dragon | move1cat = Special\n| move2 = Muddy Water | move2type = Water | move2cat = Special\n| move3 = Fire Blast | move3type = Fire | move3cat = Special\n| move4 = Focus Blast | move4type = Fighting | move4cat = Special\n}}\n{{Pok\u00e9mon\n| gen = 6\n| ndex = 0282\n| pokemon = Gardevoir\n| icon = mega\n| gender = female\n| level = 68\n| type1 = Psychic\n| type2 = Fairy\n| ability = Trace\n| held = Gardevoirite\n| move1 = Moonblast | move1type = Fairy | move1cat = Special\n| move2 = Psychic | move2type = Psychic | move2cat = Special\n| move3 = Shadow Ball | move3type = Ghost | move3cat = Special\n| move4 = Thunderbolt | move4type = Electric | move4cat = Special\n}}\n{{Party/end}}\n\n=====[[Battle Chateau]] - No Writ of Challenge=====\n{{Party\n| background = F3F7FA\n| border = BAC5D7\n| headcolor = E8E48E\n| sprite = VSDiantha.png\n| size = 150px\n| prize = {{pdollar}}14,400{{tt|*|21,600 when Gold Writ of Invitation is in effect}}\n| class=Grand Duchess\n| name = Diantha\n| location = Battle Chateau\n| game = XY\n| pokemon = 4\n}}\n{{Pok\u00e9mon\n| gen = 6\n| ndex = 0701\n| pokemon = Hawlucha\n| gender = female\n| level = 60\n| type1 = Fighting\n| type2 = Flying\n| ability = Limber\n| move1 = Swords Dance | move1type = Normal | move1cat = Status\n| move2 = Flying Press | move2type = Fighting | move2cat = Physical\n| move3 = X-Scissor | move3type = Bug | move3cat = Physical\n| move4 = Poison Jab | move4type = Poison | move4cat = Physical\n}}\n{{Pok\u00e9mon\n| gen = 6\n| ndex = 0711\n| pokemon = Gourgeist\n| gender = female\n| level = 60<br>{{color2|000|List of Pok\u00e9mon with form differences#Gourgeist|Average Size}}\n| type1 = Ghost\n| type2 = Grass\n| ability = Pickup\n| move1 = Trick-or-Treat | move1type = Ghost | move1cat = Status\n| move2 = Phantom Force | move2type = Ghost | move2cat = Physical\n| move3 = Seed Bomb | move3type = Grass | move3cat = Physical\n| move4 = Shadow Sneak | move4type = Ghost | move4cat = Physical\n}}\n{{Pok\u00e9mon\n| gen = 6\n| ndex = 0706\n| pokemon = Goodra\n| gender = female\n| level = 60\n| type1 = Dragon\n| ability = Sap Sipper\n| move1 = Dragon Pulse | move1type = Dragon | move1cat = Special\n| move2 = Muddy Water | move2type = Water | move2cat = Special\n| move3 = Fire Blast | move3type = Fire | move3cat = Special\n| move4 = Focus Blast | move4type = Fighting | move4cat = Special\n}}\n{{Pok\u00e9mon\n| gen = 6\n| ndex = 0282\n| pokemon = Gardevoir\n| icon = mega\n| gender = female\n| level = 60\n| type1 = Psychic\n| type2 = Fairy\n| ability = Trace\n| held = Gardevoirite\n| move1 = Moonblast | move1type = Fairy | move1cat = Special\n| move2 = Psychic | move2type = Psychic | move2cat = Special\n| move3 = Shadow Ball | move3type = Ghost | move3cat = Special\n| move4 = Thunderbolt | move4type = Electric | move4cat = Special\n}}\n{{Party/end}}\n\n=====[[Battle Chateau]] - Writ of Challenge=====\n{{Party\n| background = F3F7FA\n| border = BAC5D7\n| headcolor = E8E48E\n| sprite = VSDiantha.png\n| size = 150px\n| prize = {{pdollar}}15,600\n|class=Grand Duchess\n| name = Diantha\n| location = Battle Chateau\n| game = XY\n| pokemon = 4\n}}\n{{Pok\u00e9mon\n| gen = 6\n| ndex = 0701\n| pokemon = Hawlucha\n| gender = female\n| level = 65\n| type1 = Fighting\n| type2 = Flying\n| ability = Limber\n| move1 = High Jump Kick | move1type = Fighting | move1cat = Physical\n| move2 = Sky Attack | move2type = Flying | move2cat = Physical\n| move3 = Sky Drop | move3type = Flying | move3cat = Physical\n| move4 = Swords Dance | move4type = Normal | move4cat = Status\n}}\n{{Pok\u00e9mon\n| gen = 6\n| ndex = 0711\n| pokemon = Gourgeist\n| gender = female\n| level = 65<br>{{color2|000|List of Pok\u00e9mon with form differences#Gourgeist|Average Size}}\n| type1 = Ghost\n| type2 = Grass\n| ability = Pickup\n| move1 = Trick-or-Treat | move1type = Ghost | move1cat = Status\n| move2 = Pain Split | move2type = Normal | move2cat = Status\n| move3 = Seed Bomb | move3type = Grass | move3cat = Physical\n| move4 = Phantom Force | move4type = Ghost | move4cat = Physical\n}}\n{{Pok\u00e9mon\n| gen = 6\n| ndex = 0706\n| pokemon = Goodra\n| gender = female\n| level = 65\n| type1 = Dragon\n| ability = Sap Sipper\n| move1 = Dragon Pulse | move1type = Dragon | move1cat = Special\n| move2 = Aqua Tail | move2type = Water | move2cat = Physical\n| move3 = Power Whip | move3type = Grass | move3cat = Physical\n| move4 = Outrage | move4type = Dragon | move4cat = Physical\n}}\n{{Pok\u00e9mon\n| gen = 6\n| ndex = 0282\n| pokemon = Gardevoir\n| icon = mega\n| gender = female\n| level = 65\n| type1 = Psychic\n| type2 = Fairy\n| ability = Trace\n| held = Gardevoirite\n| move1 = Imprison | move1type = Psychic | move1cat = Status\n| move2 = Future Sight | move2type = Psychic | move2cat = Special\n| move3 = Captivate | move3type = Normal | move3cat = Status\n| move4 = Hypnosis | move4type = Psychic | move4cat = Status\n}}\n{{Party/end}}\n=====[[Battle Chateau]] - Blue Writ of Challenge=====\n{{Party\n| background = F3F7FA\n| border = BAC5D7\n| headcolor = E8E48E\n| sprite = VSDiantha.png\n| size = 150px\n| prize = {{pdollar}}12,000\n|class=Grand Duchess\n| name = Diantha\n| location = Battle Chateau\n| game = XY\n| pokemon = 4\n}}\n{{Pok\u00e9mon\n| gen = 6\n| ndex = 0701\n| pokemon = Hawlucha\n| gender = female\n| level = 50\n| type1 = Fighting\n| type2 = Flying\n| ability = Limber\n| move1 = Endeavor | move1type = Normal | move1cat = Physical\n| move2 = Feather Dance | move2type = Flying | move2cat = Status\n| move3 = High Jump Kick | move3type = Fighting | move3cat = Physical\n| move4 = Sky Attack | move4type = Flying | move4cat = Physical\n}}\n{{Pok\u00e9mon\n| gen = 6\n| ndex = 0711\n| pokemon = Gourgeist\n| gender = female\n| level = 50<br>{{color2|000|List of Pok\u00e9mon with form differences#Gourgeist|Average Size}}\n| type1 = Ghost\n| type2 = Grass\n| ability = Pickup\n| move1 = Shadow Ball | move1type = Ghost | move1cat = Special\n| move2 = Trick-or-Treat | move2type = Ghost | move2cat = Status\n| move3 = Pain Split | move3type = Normal | move3cat = Status\n| move4 = Seed Bomb | move4type = Grass | move4cat = Physical\n}}\n{{Pok\u00e9mon\n| gen = 6\n| ndex = 0706\n| pokemon = Goodra\n| gender = female\n| level = 50\n| type1 = Dragon\n| ability = Sap Sipper\n| move1 = Body Slam | move1type = Normal | move1cat = Physical\n| move2 = Muddy Water | move2type = Water | move2cat = Special\n| move3 = Dragon Pulse | move3type = Dragon | move3cat = Special\n| move4 = Aqua Tail | move4type = Water | move4cat = Physical\n}}\n{{Pok\u00e9mon\n| gen = 6\n| ndex = 0282\n| pokemon = Gardevoir\n| icon = mega\n| gender = female\n| level = 50\n| type1 = Psychic\n| type2 = Fairy\n| ability = Trace\n| held = Gardevoirite\n| move1 = Heal Pulse | move1type = Psychic | move1cat = Status\n| move2 = Calm Mind | move2type = Psychic | move2cat = Status\n| move3 = Psychic | move3type = Psychic | move3cat = Special\n| move4 = Imprison | move4type = Psychic | move4cat = Status\n}}\n{{Party/end}}\n\n=====[[Battle Chateau]] - Red Writ of Challenge=====\n{{Party\n| background = F3F7FA\n| border = BAC5D7\n| headcolor = E8E48E\n| sprite = VSDiantha.png\n| size = 150px\n| prize = {{pdollar}}16,800\n|class=Grand Duchess\n| name = Diantha\n| location = Battle Chateau\n| game = XY\n| pokemon = 4\n}}\n{{Pok\u00e9mon\n| gen = 6\n| ndex = 0701\n| pokemon = Hawlucha\n| gender = female\n| level = 70\n| type1 = Fighting\n| type2 = Flying\n| ability = Limber\n| move1 = High Jump Kick | move1type = Fighting | move1cat = Physical\n| move2 = Sky Attack | move2type = Flying | move2cat = Physical\n| move3 = Sky Drop | move3type = Flying | move3cat = Physical\n| move4 = Swords Dance | move4type = Normal | move4cat = Status\n}}\n{{Pok\u00e9mon\n| gen = 6\n| ndex = 0711\n| pokemon = Gourgeist\n| gender = female\n| level = 70<br>{{color2|000|List of Pok\u00e9mon with form differences#Gourgeist|Average Size}}\n| type1 = Ghost\n| type2 = Grass\n| ability = Pickup\n| move1 = Pain Split | move1type = Normal | move1cat = Status\n| move2 = Seed Bomb | move2type = Grass | move2cat = Physical\n| move3 = Phantom Force | move3type = Ghost | move3cat = Physical\n| move4 = Shadow Ball | move4type = Ghost | move4cat = Special\n}}\n{{Pok\u00e9mon\n| gen = 6\n| ndex = 0706\n| pokemon = Goodra\n| gender = female\n| level = 70\n| type1 = Dragon\n| ability = Sap Sipper\n| move1 = Dragon Pulse | move1type = Dragon | move1cat = Special\n| move2 = Aqua Tail | move2type = Water | move2cat = Physical\n| move3 = Power Whip | move3type = Grass | move3cat = Physical\n| move4 = Outrage | move4type = Dragon | move4cat = Physical\n}}\n{{Pok\u00e9mon\n| gen = 6\n| ndex = 0282\n| pokemon = Gardevoir\n| icon = mega\n| gender = female\n| level = 70\n| type1 = Psychic\n| type2 = Fairy\n| ability = Trace\n| held = Gardevoirite\n| move1 = Imprison | move1type = Psychic | move1cat = Status\n| move2 = Future Sight | move2type = Psychic | move2cat = Special\n| move3 = Captivate | move3type = Normal | move3cat = Status\n| move4 = Hypnosis | move4type = Psychic | move4cat = Status\n}}\n{{Party/end}}\n\n=====[[Battle Chateau]] - Black Writ of Challenge=====\n{{Party\n| background = F3F7FA\n| border = BAC5D7\n| headcolor = E8E48E\n| sprite = VSDiantha.png\n| size = 150px\n| prize = {{pdollar}}19,200\n|class=Grand Duchess\n| name = Diantha\n| location = Battle Chateau\n| game = XY\n| pokemon = 4\n}}\n{{Pok\u00e9mon\n| gen = 6\n| ndex = 0701\n| pokemon = Hawlucha\n| gender = female\n| level = 80\n| type1 = Fighting\n| type2 = Flying\n| ability = Limber\n| move1 = High Jump Kick | move1type = Fighting | move1cat = Physical\n| move2 = Sky Attack | move2type = Flying | move2cat = Physical\n| move3 = Sky Drop | move3type = Flying | move3cat = Physical\n| move4 = Swords Dance | move4type = Normal | move4cat = Status\n}}\n{{Pok\u00e9mon\n| gen = 6\n| ndex = 0711\n| pokemon = Gourgeist\n| gender = female\n| level = 80<br>{{color2|000|List of Pok\u00e9mon with form differences#Gourgeist|Average Size}}\n| type1 = Ghost\n| type2 = Grass\n| ability = Pickup\n| move1 = Seed Bomb | move1type = Grass | move1cat = Physical\n| move2 = Phantom Force | move2type = Ghost | move2cat = Physical\n| move3 = Shadow Ball | move3type = Ghost | move3cat = Special\n| move4 = Explosion | move4type = Normal | move4cat = Physical\n}}\n{{Pok\u00e9mon\n| gen = 6\n| ndex = 0706\n| pokemon = Goodra\n| gender = female\n| level = 80\n| type1 = Dragon\n| ability = Sap Sipper\n| move1 = Dragon Pulse | move1type = Dragon | move1cat = Special\n| move2 = Aqua Tail | move2type = Water | move2cat = Physical\n| move3 = Power Whip | move3type = Grass | move3cat = Physical\n| move4 = Outrage | move4type = Dragon | move4cat = Physical\n}}\n{{Pok\u00e9mon\n| gen = 6\n| ndex = 0282\n| pokemon = Gardevoir\n| icon = mega\n| gender = female\n| level = 80\n| type1 = Psychic\n| type2 = Fairy\n| ability = Trace\n| held = Gardevoirite\n| move1 = Captivate | move1type = Normal | move1cat = Status\n| move2 = Hypnosis | move2type = Psychic | move2cat = Status\n| move3 = Dream Eater | move3type = Psychic | move3cat = Special\n| move4 = Stored Power | move4type = Psychic | move4cat = Special\n}}\n{{Party/end}}\n\n=====[[Trade]]d to the player=====\nAfter becoming {{pkmn|Champion}}, Diantha will appear at [[South Boulevard|Caf\u00e9 Soleil]] in [[Lumiose City]]. She will trade a {{p|Ralts}} holding [[Gardevoirite]] for any Pok\u00e9mon the player has in their [[party]].\n\n{{Gen6ievent\n|pokemon=Ralts\n|ndex=0280\n|gender=f\n|level=5\n|ball=Pok\u00e9\n|type=Psychic|type2=Fairy\n|ot=Diantha\n|id=37110\n|met=a Link Trade\n|nature=Modest\n|hpiv=20\n|atkiv=20\n|defiv=20\n|spaiv=31\n|spdiv=20\n|speiv=31\n|item=Gardevoirite\n|move1=Growl|move1type=Normal|move1cat=Status|move1rel=yes\n|ability=Synchronize\n|gift=yes\n|trade=yes\n|method=[[In-game trade]]\n}}"}}}