{"parse": {"title": "Jupiter", "pageid": 13693, "redirects": [], "wikitext": {"*": "===={{game|Diamond and Pearl|s}}====\n=====First battle=====\n{{Party\n| background = {{silver color}}\n| border = {{dark color}}\n| headcolor = EE8BCD\n| sprite = Spr DP Jupiter.png\n| prize = {{Pdollar}}1600\n| class = Commander\n| name = Jupiter\n| location = Team Galactic Eterna Building\n| game = DP\n| pokemon = 2\n}}\n{{Pok\u00e9mon\n| gen = 4\n| ndex = 0041\n| pokemon = Zubat\n| gender = female\n| level = 18\n| type1 = Poison\n| type2 = Flying\n| ability = Inner Focus\n| move1 = Giga Drain | move1type = Grass | move1cat = Special\n| move2 = Wing Attack | move2type = Flying | move2cat = Physical\n| move3 = Bite | move3type = Dark | move3cat = Physical\n}}\n{{Pok\u00e9mon\n| gen = 4\n| ndex = 0435\n| pokemon = Skuntank\n| gender = female\n| level = 20\n| type1 = Poison\n| type2 = Dark\n| ability = Stench\n| held = Sitrus Berry\n| move1 = Night Slash | move1type = Dark | move1cat = Physical\n| move2 = Poison Gas | move2type = Poison | move2cat = Status\n| move3 = Screech | move3type = Normal | move3cat = Status\n| move4 = SmokeScreen | move4type = Normal | move4cat = Status\n}}\n{{Party/end}}\n=====Second battle ([[Multi Battle]] with [[Mars]])=====\n{{Party/2\n| background = {{silver color}}\n| bordercolor = {{dark color}}\n| headcolor = {{silver color light}}\n| location = Spear Pillar\n| game = DP\n| prize = {{pdollar}}7280\n| t-background = F69C7B\n| t-border = 9C2931\n| sprite = Spr DP Mars.png\n| class = Commander\n| name = {{color2|000|Mars}}\n| pokemon = 3\n| t-background2 = EE8BCD\n| t-border2 = D56AAC\n| sprite2 = Spr DP Jupiter.png\n| class2 = Commander\n| name2 = Jupiter\n| pokemon2 = 3\n}}\n{{Pok\u00e9mon\n| gen = 4\n| ndex = 0436\n| pokemon = Bronzor\n| gender = none\n| level = 41\n| type1 = Steel\n| type2 = Psychic\n| ability = Levitate\n| move1 = Gyro Ball | move1type = Steel | move1cat = Physical\n| move2 = Extrasensory | move2type = Psychic | move2cat = Special\n| move3 = Light Screen | move3type = Psychic | move3cat = Status\n| move4 = Confuse Ray | move4type = Ghost | move4cat = Status\n}}\n{{Pok\u00e9mon\n| gen = 4\n| ndex = 0042\n| pokemon = Golbat\n| gender = female\n| level = 42\n| type1 = Poison\n| type2 = Flying\n| ability = Inner Focus\n| move1 = Air Cutter | move1type = Flying | move1cat = Special\n| move2 = Bite | move2type = Dark | move2cat = Physical\n| move3 = Poison Fang | move3type = Poison | move3cat = Physical\n| move4 = Confuse Ray | move4type = Ghost | move4cat = Status\n}}\n{{Pok\u00e9mon\n| gen = 4\n| ndex = 0432\n| pokemon = Purugly\n| gender = female\n| level = 45\n| type1 = Normal\n| ability = Thick Fat\n| held = Sitrus Berry\n| move1 = Slash | move1type = Normal | move1cat = Physical\n| move2 = Shadow Claw | move2type = Ghost | move2cat = Physical\n| move3 = Aerial Ace | move3type = Flying | move3cat = Physical\n| move4 = Hypnosis | move4type = Psychic | move4cat = Status\n}}\n{{Party/2/div|t-background2 = EE8BCD}}\n{{Pok\u00e9mon\n| gen = 4\n| ndex = 0436\n| pokemon = Bronzor\n| gender = none\n| level = 41\n| type1 = Steel\n| type2 = Psychic\n| ability = Levitate\n| move1 = Gyro Ball | move1type = Steel | move1cat = Physical\n| move2 = Extrasensory | move2type = Psychic | move2cat = Special\n| move3 = Rock Slide | move3type = Rock | move3cat = Physical\n| move4 = Reflect | move4type = Psychic | move4cat = Status\n}}\n{{Pok\u00e9mon\n| gen = 4\n| ndex = 0042\n| pokemon = Golbat\n| gender = female\n| level = 41\n| type1 = Poison\n| type2 = Flying\n| ability = Inner Focus\n| move1 = Sludge Bomb | move1type = Poison | move1cat = Special\n| move2 = Air Cutter | move2type = Flying | move2cat = Special\n| move3 = Giga Drain | move3type = Grass | move3cat = Special\n| move4 = Mean Look | move4type = Normal | move4cat = Status\n}}\n{{Pok\u00e9mon\n| gen = 4\n| ndex = 0435\n| pokemon = Skuntank\n| gender = female\n| level = 46\n| type1 = Poison\n| type2 = Dark\n| ability = Stench\n| held = Sitrus Berry\n| move1 = Night Slash | move1type = Dark | move1cat = Physical\n| move2 = Poison Jab | move2type = Poison | move2cat = Physical\n| move3 = Flamethrower | move3type = Fire | move3cat = Special\n| move4 = SmokeScreen | move4type = Normal | move4cat = Status\n}}\n{{Party/end}}"}}}