{"parse": {"title": "Janine", "pageid": 2969, "redirects": [], "wikitext": {"*": "===={{game|HeartGold and SoulSilver|s}}====\n=====Gym battle=====\nJanine has three [[Full Restore]]s.{{Party\n| background = {{poison color}}\n| border = {{poison color dark}}\n| headcolor = {{poison color light}}\n| sprite = Spr HGSS Janine.png\n| prize = {{pdollar}}6000\n| class = Leader\n| classlink = Gym Leader\n| name = Janine\n| location = Fuchsia Gym\n| game = HGSS\n| pokemon = 5\n}}\n{{Pok\u00e9mon\n| gen = 4\n| ndex = 0169\n| pokemon = Crobat\n| gender = female\n| level = 47\n| type1 = Poison\n| type2 = Flying\n| ability = Inner Focus\n| move1 = Confuse Ray | move1type = Ghost | move1cat = Status\n| move2 = Screech | move2type = Normal | move2cat = Status\n| move3 = Wing Attack | move3type = Flying | move3cat = Physical\n| move4 = Supersonic | move4type = Normal | move4cat = Status\n}}\n{{Pok\u00e9mon\n| gen = 4\n| ndex = 0110\n| pokemon = Weezing\n| gender = female\n| level = 44\n| type1 = Poison\n| ability = Levitate\n| move1 = Sludge Bomb | move1type = Poison | move1cat = Special\n| move2 = Toxic | move2type = Poison | move2cat = Status\n| move3 = Explosion | move3type = Normal | move3cat = Physical\n| move4 = Double Hit | move4type = Normal | move4cat = Physical\n}}\n{{Pok\u00e9mon\n| gen = 4\n| ndex = 0168\n| pokemon = Ariados\n| gender = female\n| level = 47\n| type1 = Bug\n| type2 = Poison\n| ability = Insomnia\n| move1 = Swagger | move1type = Normal | move1cat = Status\n| move2 = Night Shade | move2type = Ghost | move2cat = Special\n| move3 = Poison Jab | move3type = Poison | move3cat = Physical\n| move4 = Pin Missile | move4type = Bug | move4cat = Physical\n}}\n{{Pok\u00e9mon\n| gen = 4\n| ndex = 0168\n| pokemon = Ariados\n| gender = female\n| level = 47\n| type1 = Bug\n| type2 = Poison\n| ability = Insomnia\n| move1 = Psychic | move1type = Psychic | move1cat = Special\n| move2 = Poison Jab | move2type = Poison | move2cat = Physical\n| move3 = Scary Face | move3type = Normal | move3cat = Status\n| move4 = Pin Missile | move4type = Bug | move4cat = Physical\n}}\n{{Pok\u00e9mon\n| gen = 4\n| ndex = 0049\n| pokemon = Venomoth\n| gender = female\n| level = 50\n| type1 = Bug\n| type2 = Poison\n| ability = Tinted Lens\n| held = Sitrus Berry\n| move1 = Double Team | move1type = Normal | move1cat = Status\n| move2 = Psychic | move2type = Psychic | move2cat = Special\n| move3 = Sludge Bomb | move3type = Poison | move3cat = Special\n| move4 = Signal Beam | move4type = Bug | move4cat = Special\n}}\n{{Party/end}}\n=====[[Rematch]]=====\nJanine has three [[Full Restore]]s.{{Party\n| background = {{poison color}}\n| border = {{poison color dark}}\n| headcolor = {{poison color light}}\n| sprite = Spr HGSS Janine.png\n| prize = {{pdollar}}6600\n| class = Leader\n| classlink = Gym Leader\n| name = Janine\n| location = Fighting Dojo\n| game = HGSS\n| pokemon = 6\n}}\n{{Pok\u00e9mon\n| gen = 4\n| ndex = 0169\n| pokemon = Crobat\n| gender = female\n| level = 52\n| type1 = Poison\n| type2 = Flying\n| ability = Inner Focus\n| move1 = Heat Wave | move1type = Fire | move1cat = Special\n| move2 = Cross Poison | move2type = Poison | move2cat = Physical\n| move3 = Confuse Ray | move3type = Ghost | move3cat = Status\n| move4 = U-turn | move4type = Bug | move4cat = Physical\n}}\n{{Pok\u00e9mon\n| gen = 4\n| ndex = 0110\n| pokemon = Weezing\n| gender = female\n| level = 56\n| type1 = Poison\n| ability = Levitate\n| move1 = Thunderbolt | move1type = Electric | move1cat = Special\n| move2 = Sludge Bomb | move2type = Poison | move2cat = Special\n| move3 = Toxic | move3type = Poison | move3cat = Status\n| move4 = Explosion | move4type = Normal | move4cat = Physical\n}}\n{{Pok\u00e9mon\n| gen = 4\n| ndex = 0454\n| pokemon = Toxicroak\n| gender = female\n| level = 52\n| type1 = Poison\n| type2 = Fighting\n| ability = Dry Skin\n| move1 = Cross Chop | move1type = Fighting | move1cat = Physical\n| move2 = Poison Jab | move2type = Poison | move2cat = Physical\n| move3 = Attract | move3type = Normal | move3cat = Status\n| move4 = Substitute | move4type = Normal | move4cat = Status\n}}\n{{Pok\u00e9mon\n| gen = 4\n| ndex = 0168\n| pokemon = Ariados\n| gender = female\n| level = 58\n| type1 = Bug\n| type2 = Poison\n| ability = Insomnia\n| move1 = Bounce | move1type = Flying | move1cat = Physical\n| move2 = Toxic | move2type = Poison | move2cat = Status\n| move3 = Swagger | move3type = Normal | move3cat = Status\n| move4 = Night Shade | move4type = Ghost | move4cat = Special\n}}\n{{Pok\u00e9mon\n| gen = 4\n| ndex = 0049\n| pokemon = Venomoth\n| gender = female\n| level = 59\n| type1 = Bug\n| type2 = Poison\n| ability = Tinted Lens\n| held = Sitrus Berry\n| move1 = Psychic | move1type = Psychic | move1cat = Special\n| move2 = Bug Buzz | move2type = Bug | move2cat = Special\n| move3 = Sleep Powder | move3type = Grass | move3cat = Status\n| move4 = Double Team | move4type = Normal | move4cat = Status\n}}\n{{Pok\u00e9mon\n| gen = 4\n| ndex = 0452\n| pokemon = Drapion\n| gender = female\n| level = 55\n| type1 = Poison\n| type2 = Dark\n| ability = Sniper\n| move1 = Confuse Ray | move1type = Ghost | move1cat = Status\n| move2 = Swords Dance | move2type = Normal | move2cat = Status\n| move3 = Cross Poison | move3type = Poison | move3cat = Physical\n| move4 = Crunch | move4type = Dark | move4cat = Physical\n}}\n{{Party/end}}"}}}