{"parse": {"title": "Katherine (Kalos)", "pageid": 204645, "redirects": [{"from": "Karen (anime)", "to": "Katherine (Kalos)"}], "wikitext": {"*": "===Pok\u00e9mon===\n{{Party\n| background = {{fairy color}}\n| border = {{fairy color dark}}\n| headcolor = {{fairy color light}}\n| sprite = VSFurisode Girl 4.png{{!}}150px\n| prize = {{pdollar}}2,880\n| class = Furisode Girl\n| name = Katherine\n| location = Laverre Gym\n| game = XY\n| pokemon = 1\n}}\n{{Pok\u00e9mon\n| gen = 6\n| ndex = 0685\n| pokemon = Slurpuff\n| gender = female\n| level = 40\n| type1 = Fairy\n| ability = Sweet Veil\n| move1 = Energy Ball | move1type = Grass | move1cat = Special\n| move2 = Draining Kiss | move2type = Fairy | move2cat = Special\n| move3 = Aromatherapy | move3type = Grass | move3cat = Status\n| move4 = Endeavor | move4type = Normal | move4cat = Physical\n}}\n{{Party/end}}"}}}