{"parse": {"title": "Lysandre", "pageid": 185099, "redirects": [], "wikitext": {"*": "===Pok\u00e9mon Generations===\n{{MissingInfo|1|enva}}\n[[File:Lysandre PG.png|thumb|250px|Lysandre in [[Pok\u00e9mon Generations]]]]\nLysandre appeared in ''[[PG16|The Beauty Eternal]]'', where he announced the release of the [[Holo Caster]]. In the process, he was depicted as a popular and successful businessman. He was later seen discussing with [[Diantha]] about the concept of eternal beauty. Afterwards, he was interviewed by some reporters over his involvement with some secret plans, but he didn't reveal any information. Lysandre was then seen at the [[Team Flare Secret HQ]], conducting experiments on {{p|Yveltal}} in the hopes of creating a more beautiful world.\n\n====Pok\u00e9mon====\n=====On hand=====\n{{anchor|Pyroar 2}}{{TrainerPok\u00e9\n|width=68%\n|main=yes\n|trainer=Lysandre\n|pkmn=Pyroar\n|gender=male\n|type1=Fire\n|type2=Normal\n|img=Lysandre Pyroar PG.png\n|epnum=PG16\n|epname=The Beauty Eternal\n|desc={{p|Pyroar}} is Lysandre's only known Pok\u00e9mon.}}\n\n=====Held captive=====\n{{TrainerPok\u00e9\n|trainer=Lysandre\n|pkmn=Yveltal\n|type1=Dark\n|type2=Flying\n|img=Yveltal PG.png\n|epnum=PG16\n|epname=The Beauty Eternal\n|desc={{p|Yveltal}} was first seen as a cocoon in the [[Team Flare Secret HQ]]. Lysandre conducted some experiments on Yveltal in the hopes of creating a more beautiful world.\n\nNone of Yveltal's moves are known.}}\n\n====Voice actors====\n{{vatable|color=eb8b51|bordercolor=ab3f26\n|ja=\u6771\u5730\u5b8f\u6a39 ''[[Hiroki Touchi]]''\n|en=Dean Wein\n|nl=Hein van Beem\n|pt_br=M\u00e1rcio Sim\u00f5es\n|es_eu=Ernesto Casta\u00f1o}}"}}}