{"parse": {"title": "Lorelei", "pageid": 2736, "redirects": [], "wikitext": {"*": "===Pok\u00e9mon Zensho===\n[[File:Lorelei Zensho.png|thumb|100px|Lorelei in Pok\u00e9mon Zensho]]\nIn [[PZ10]], as the first member of the Elite Four, Lorelei battles {{Zensho|Satoshi}} with her Cloyster. She is defeated, allowing Satoshi to move on to the next room to face [[Bruno]].\n\n====Pok\u00e9mon====\n{| style=\"float:left; width: 25%\"\n|-\n| {{InactivePok\u00e9|Lorelei|Cloyster|Lorelei Cloyster Zensho.png|Water|Ice|link=Lorelei's Cloyster#In the Pok\u00e9mon Zensho manga}}\n|}\n{{-}}"}}}