{"parse": {"title": "Larry", "pageid": 277517, "redirects": [], "wikitext": {"*": "===Pok\u00e9mon===\nAs a Gym Leader, Larry's team consists of {{t|Normal}} types, while he uses {{t|Flying}} types as an Elite Four member. In the rematch with him at the [[Blueberry Academy]]'s [[League Club Room]], his team will be made up of both Normal and Flying types. His signature Pok\u00e9mon is {{p|Staraptor}}.\n\n====Gym battle====\nLarry will {{Tera}}stallize his {{p|Staraptor}} at the first opportunity.\n{{Party\n| background = {{normal color}}\n| border = {{normal color dark}}\n| headcolor = {{normal color light}}\n| sprite = VSLarry.png\n| size = x100px\n| prize = {{PDollar}}6,480\n| class = Gym Leader\n| name = Larry\n| location = Medali Gym\n| game = SV\n| pokemon = 3\n}}\n{{Pok\u00e9mon\n| gen = 9\n| ndex = 0775\n| pokemon = Komala\n| gender = female\n| level = 35\n| type1 = Normal\n| ability = Comatose\n| move1 = Yawn | move1type = Normal | move1cat = Status\n| move2 = Sucker Punch | move2type = Dark | move2cat = Physical\n| move3 = Slam | move3type = Normal | move3cat = Physical\n}}\n{{Pok\u00e9mon\n| gen = 9\n| ndex = 0982\n| pokemon = Dudunsparce\n| gender = female\n| level = 35\n| type1 = Normal\n| ability = Serene Grace\n| move1 = Hyper Drill | move1type = Normal | move1cat = Physical\n| move2 = Drill Run | move2type = Ground | move2cat = Physical\n| move3 = Glare | move3type = Normal | move3cat = Status\n}}\n{{Pok\u00e9mon\n| gen = 9\n| ndex = 0398\n| pokemon = Staraptor\n| gender = male\n| level = 36\n| type1 = Normal\n| type2 = Flying\n| tera = Normal\n| icon = tera\n| ability = Intimidate\n| move1 = Facade | move1type = Normal | move1cat = Physical\n| move2 = Aerial Ace | move2type = Flying | move2cat = Physical\n}}\n{{Party/end}}\n====Champion Assessment====\nLarry will {{Tera}}stallize his {{p|Flamigo}} at the first opportunity.\n{{Party\n| background = {{flying color}}\n| border = {{flying color dark}}\n| headcolor = {{flying color light}}\n| sprite = VSLarry 2.png\n| size = x100px\n| prize = {{PDollar}}12,720\n| name = Larry\n| class2 = of the Elite Four\n| classlink2 = Elite Four\n| location = Pok\u00e9mon League (Paldea)\n| locationname = Pok\u00e9mon League\n| game = SV\n| pokemon = 5\n}}\n{{Pok\u00e9mon\n| gen = 9\n| ndex = 0357\n| pokemon = Tropius\n| gender = male\n| level = 59\n| type1 = Grass\n| type2 = Flying\n| ability = Chlorophyll\n| move1 = Air Slash | move1type = Flying | move1cat = Special\n| move2 = Solar Beam | move2type = Grass | move2cat = Special\n| move3 = Dragon Pulse | move3type = Dragon | move3cat = Special\n| move4 = Sunny Day | move4type = Fire | move4cat = Status\n}}\n{{Pok\u00e9mon\n| gen = 9\n| ndex = 0741\n| pokemon = Oricorio\n| form = -Pom-Pom\n| gender = female\n| level = 59\n| type1 = Electric\n| type2 = Flying\n| ability = Dancer\n| move1 = Revelation&nbsp;Dance | move1type = Electric | move1cat = Special\n| move2 = Air Slash | move2type = Flying | move2cat = Special\n| move3 = Teeter Dance | move3type = Normal | move3cat = Status\n| move4 = Icy Wind | move4type = Ice | move4cat = Special\n}}\n{{Pok\u00e9mon\n| gen = 9\n| ndex = 0334\n| pokemon = Altaria\n| gender = female\n| level = 59\n| type1 = Dragon\n| type2 = Flying\n| ability = Natural Cure\n| move1 = Moonblast | move1type = Fairy | move1cat = Special\n| move2 = Flamethrower | move2type = Fire | move2cat = Special\n| move3 = Ice Beam | move3type = Ice | move3cat = Special\n| move4 = Dragon Pulse | move4type = Dragon | move4cat = Special\n}}\n{{Pok\u00e9mon\n| gen = 9\n| ndex = 0398\n| pokemon = Staraptor\n| gender = male\n| level = 59\n| type1 = Normal\n| type2 = Flying\n| ability = Intimidate\n| move1 = Facade | move1type = Normal | move1cat = Physical\n| move2 = Brave Bird | move2type = Flying | move2cat = Physical\n| move3 = Close Combat | move3type = Fighting | move3cat = Physical\n| move4 = Thief | move4type = Dark | move4cat = Physical\n}}\n{{Pok\u00e9mon\n| gen = 9\n| ndex = 0973\n| pokemon = Flamigo\n| gender = male\n| level = 60\n| type1 = Flying\n| type2 = Fighting\n| tera = Flying\n| icon = tera\n| ability = Scrappy\n| move1 = Brave Bird | move1type = Flying | move1cat = Physical\n| move2 = Close Combat | move2type = Fighting | move2cat = Physical\n| move3 = Throat Chop | move3type = Dark | move3cat = Physical\n| move4 = Liquidation | move4type = Water | move4cat = Physical\n}}\n{{Party/end}}\n====[[Rematch]]====\nLarry will {{Tera}}stallize his {{p|Staraptor}} at the first opportunity.\n{{Party\n| background = {{normal color}}\n| border = {{normal color dark}}\n| headcolor = {{normal color light}}\n| sprite = VSLarry.png\n| size = x100px\n| prize = {{PDollar}}11,880\n| class = Gym Leader\n| name = Larry\n| location = Medali Gym\n| game = SV\n| pokemon = 5\n}}\n{{Pok\u00e9mon\n| gen = 9\n| ndex = 0916\n| pokemon = Oinkologne\n| form = -Female\n| gender = female\n| level = 65\n| type1 = Normal\n| ability = Gluttony\n| move1 = Body Slam | move1type = Normal | move1cat = Physical\n| move2 = Bullet Seed | move2type = Grass | move2cat = Physical\n| move3 = Zen Headbutt | move3type = Psychic | move3cat = Physical\n| move4 = Iron Head | move4type = Steel | move4cat = Physical\n}}\n{{Pok\u00e9mon\n| gen = 9\n| ndex = 0775\n| pokemon = Komala\n| gender = female\n| level = 65\n| type1 = Normal\n| ability = Comatose\n| move1 = Yawn | move1type = Normal | move1cat = Status\n| move2 = Sucker Punch | move2type = Dark | move2cat = Physical\n| move3 = Wood Hammer | move3type = Grass | move3cat = Physical\n| move4 = Zen Headbutt | move4type = Psychic | move4cat = Physical\n}}\n{{Pok\u00e9mon\n| gen = 9\n| ndex = 0628\n| pokemon = Braviary\n| gender = male\n| level = 65\n| type1 = Normal\n| type2 = Flying\n| ability = Keen Eye\n| move1 = Brave Bird | move1type = Flying | move1cat = Physical\n| move2 = Crush Claw | move2type = Normal | move2cat = Physical\n| move3 = Close Combat | move3type = Fighting | move3cat = Physical\n| move4 = Rock Tomb | move4type = Rock | move4cat = Physical\n}}\n{{Pok\u00e9mon\n| gen = 9\n| ndex = 0982\n| pokemon = Dudunsparce\n| gender = male\n| level = 65\n| type1 = Normal\n| ability = Serene Grace\n| move1 = Hyper Drill | move1type = Normal | move1cat = Physical\n| move2 = Drill Run | move2type = Ground | move2cat = Physical\n| move3 = Dragon Rush | move3type = Dragon | move3cat = Physical\n| move4 = Stone Edge | move4type = Rock | move4cat = Physical\n}}\n{{Pok\u00e9mon\n| gen = 9\n| ndex = 0398\n| pokemon = Staraptor\n| gender = male\n| level = 66\n| type1 = Normal\n| type2 = Flying\n| tera = Normal\n| icon = tera\n| ability = Intimidate\n| move1 = Facade | move1type = Normal | move1cat = Physical\n| move2 = Brave Bird | move2type = Flying | move2cat = Physical\n| move3 = Close Combat | move3type = Fighting | move3cat = Physical\n| move4 = Thief | move4type = Dark | move4cat = Physical\n}}\n{{Party/end}}\n====[[League Club Room]]====\nLarry will {{Tera}}stallize his {{p|Staraptor}} at the first opportunity.\n{{Party\n| background = {{normal color}}\n| border = {{normal color dark}}\n| headcolor = {{flying color light}}\n| sprite = VSLarry.png\n| size = x100px\n| prize = {{PDollar}}19,920\n| class = Gym Leader\n| name = Larry\n| location = Blueberry Academy\n| game = SV\n| pokemon = 6\n}}\n{{Pok\u00e9mon\n| gen = 9\n| ndex = 0916\n| pokemon = Oinkologne\n| form = -Female\n| gender = female\n| level = 82\n| type1 = Normal\n| ability = Gluttony\n| move1 = Body Slam | move1type = Normal | move1cat = Physical\n| move2 = Trailblaze | move2type = Grass | move2cat = Physical\n| move3 = Play Rough | move3type = Fairy | move3cat = Physical\n| move4 = Iron Head | move4type = Steel | move4cat = Physical\n}}\n{{Pok\u00e9mon\n| gen = 9\n| ndex = 0128\n| pokemon = Tauros\n| gender = male\n| level = 82\n| type1 = Normal\n| ability = Intimidate\n| move1 = Raging Bull | move1type = Normal | move1cat = Physical\n| move2 = Earthquake | move2type = Ground | move2cat = Physical\n| move3 = Stone Edge | move3type = Rock | move3cat = Physical\n| move4 = Zen Headbutt | move4type = Psychic | move4cat = Physical\n}}\n{{Pok\u00e9mon\n| gen = 9\n| ndex = 0982\n| pokemon = Dudunsparce\n| gender = male\n| level = 82\n| type1 = Normal\n| ability = Serene Grace\n| move1 = Hyper Drill | move1type = Normal | move1cat = Physical\n| move2 = Earthquake | move2type = Ground | move2cat = Physical\n| move3 = Glare | move3type = Normal | move3cat = Status\n| move4 = Rock Slide | move4type = Rock | move4cat = Physical\n}}\n{{Pok\u00e9mon\n| gen = 9\n| ndex = 0334\n| pokemon = Altaria\n| gender = female\n| level = 82\n| type1 = Dragon\n| type2 = Flying\n| ability = Natural Cure\n| move1 = Moonblast | move1type = Fairy | move1cat = Special\n| move2 = Flamethrower | move2type = Fire | move2cat = Special\n| move3 = Ice Beam | move3type = Ice | move3cat = Special\n| move4 = Dual Wingbeat | move4type = Flying | move4cat = Physical\n}}\n{{Pok\u00e9mon\n| gen = 9\n| ndex = 0973\n| pokemon = Flamigo\n| gender = male\n| level = 82\n| type1 = Flying\n| type2 = Fighting\n| ability = Scrappy\n| move1 = Brave Bird | move1type = Flying | move1cat = Physical\n| move2 = Close Combat | move2type = Fighting | move2cat = Physical\n| move3 = Throat Chop | move3type = Dark | move3cat = Physical\n| move4 = Liquidation | move4type = Water | move4cat = Physical\n}}\n{{Pok\u00e9mon\n| gen = 9\n| ndex = 0398\n| pokemon = Staraptor\n| gender = male\n| level = 83\n| type1 = Normal\n| type2 = Flying\n| tera = Normal\n| icon = tera\n| ability = Intimidate\n| move1 = Facade | move1type = Normal | move1cat = Physical\n| move2 = Brave Bird | move2type = Flying | move2cat = Physical\n| move3 = Close Combat | move3type = Fighting | move3cat = Physical\n| move4 = Thief | move4type = Dark | move4cat = Physical\n}}\n{{Party/end}}\n====Traded to the player====\nUpon the third unique interaction with Larry in the League Club Room, he will trade a Dudunsparce to the player in exchange for almost any Pok\u00e9mon excluding {{Shiny}}, {{pkmn2|Legendary}}, or [[Mythical Pok\u00e9mon]].\n\n{{SVievent\n|ndex=0982\n|ball=Pok\u00e9\n|pokemon=Dudunsparce\n|form=Two-Segment Form\n|gender=m\n|level=35\n|teratype=Flying\n|type=Normal\n|ot=Larry\n|id=766634\n|ability=Serene Grace\n|nature=Relaxed\n|met=a Link Trade\n|ribbon=Partner\n|hpiv=15\n|atkiv=24\n|defiv=31\n|spaiv=31\n|spdiv=11\n|speiv=26\n|move1=Facade|move1type=Normal|move1cat=Physical\n|move2=Air Slash|move2type=Flying|move2cat=Special\n|move3=Drill Run|move3type=Ground|move3cat=Physical\n|move4=Hyper Drill|move4type=Normal|move4cat=Physical\n|method=[[In-game trade]] (League Club Room)\n|gift=yes\n|trade=yes\n|scale=128}}"}}}