{"parse": {"title": "Norman", "pageid": 877, "redirects": [], "wikitext": {"*": "====={{aniseries|AG}}=====\nIn {{aniseries|PTS}}, Norman is the father of {{an|May}} and [[Max]], two of Ash's former traveling companions, and the husband of [[Caroline]].\n\nVery early in his Hoenn journey, {{Ash}} arrived with May in Petalburg City in the hope of getting his first Gym battle. In ''[[AG003|There's no Place Like Hoenn]]'', Ash found the Petalburg Gym and met [[Max]], who posed as if he was the Gym Leader. May stopped him and allowed Ash to meet her parents, Caroline and Norman. Norman turned out be to the real [[Petalburg City]] [[Gym Leader]]. Norman used his Pok\u00e9mon, a {{p|Vigoroth}}, in an exhibition battle against Pikachu, and later to save [[May's Torchic]] from {{TRT}}.\n\nNorman is a good friend of [[Professor Birch]] and was most likely the person to send May to [[Littleroot Town]] to get her first Pok\u00e9mon. As May did not initially like Pok\u00e9mon, this seemed to have created some distance between the two. Before Ash knew that Norman was May's father, he commented that it sounded like she knew the Petalburg Gym Leader pretty well, to which she replied, \"No, I just wish I did,\" and became subdued.\n\nIn ''[[AG068|A Double Dilemma]]'', Norman appeared in flashbacks and on memorabilia. It was also revealed that he had a large fanbase in [[North Petalburg]].\n\nIn ''[[AG069|Love, Petalburg Style!]]'', when Ash and his friends visited Petalburg City again, May and Max tried to figure out why Norman and Caroline were getting all worked up as Ash tried to save Norman's three Pok\u00e9mon from Team Rocket. It all turned out that Norman had Nurse Joy set up a special firework display to make fireworks in a form of a {{p|Beautifly}} as a wedding anniversary gift for Caroline. During the episode, Norman showed that he was rather dense, not realizing that Caroline assumed that he was having an affair with Nurse Joy.\n\nAsh had his Gym battle with Norman in ''[[AG070|Balance of Power]]''. Using his {{AP|Grovyle}}, {{AP|Pikachu}}, and {{AP|Torkoal}}, Ash defeated Norman's Pok\u00e9mon. Upset by his father's loss, Max stole the Balance Badge and locked himself up in Norman's greenhouse. Norman was able to calm Max down, and Max gave Ash his {{Badge|Balance}}.\n\nHe reappeared in flashbacks in ''[[AG075|Whiscash and Ash]]'', ''[[AG089|A Scare to Remember!]]'', and ''[[AG103|A Cacturne for the Worse]]''.\n[[File:Norman Slaking DP.png|thumb|right|220px|Norman and family watching May compete in the Wallace Cup]]\nIn ''[[AG121|Hi Ho Silver Wind!]]'', Caroline joined Ash and {{ashfr}} in [[Slateport City]] to watch May compete in the [[Hoenn Grand Festival]], though revealed that Norman was too busy at the Petalburg Gym, so he would be cheering her on from home. In ''[[AG122|Deceit and Assist]]'', Norman was watching May competing in the Hoenn Grand Festival on [[television]].\n\nIn ''[[AG126|Saved by the Beldum]]'', Norman watched Ash competing in the [[Ever Grande Conference]] from the comfort of his living room.\n\nHe reappeared in a fantasy in ''[[AG153|Tactics Theatrics!]]''."}}}