{"parse": {"title": "Whitney", "pageid": 2758, "redirects": [], "wikitext": {"*": "====Pok\u00e9mon====\nThis listing is of Whitney's known {{OBP|Pok\u00e9mon|species}} in {{aniseries|PTS}}.\n\n{{TrainerPok\u00e9\n|trainer=Whitney\n|pkmn=Clefairy\n|type1=Normal\n|img=Whitney Clefairy.png\n|epnum=EP158\n|epname=A Goldenrod Opportunity\n|vajp=Mayumi Iizuka\n|vaen=Tara Jayne\n|desc=Whitney's {{p|Clefairy}} first appeared when {{AP|Pikachu}} accidentally knocked into it. After shopping, Whitney found that Clefairy was missing, having been caught by {{TRT}}. At the [[Magnet Train]] platform, it used Metronome, which turned into Gust, which in turn freed Pikachu.\n\nIt was used again as the second Pok\u00e9mon in the [[Gym]] {{pkmn|battle}} against {{Ash}}, where it went up against {{AP|Cyndaquil}}. It began with using Metronome. However, it turned into Splash. Cyndaquil used another {{m|Flamethrower}}, scaring Clefairy and forcing Whitney to withdraw it from the match.\n\nClefairy seems to be Whitney's favorite Pok\u00e9mon, as it is usually seen traveling [[Walking Pok\u00e9mon|out of its Pok\u00e9 Ball]].\n\nClefairy's only known move is {{m|Metronome}}.<br/>\nClefairy has also used {{m|Gust}} and {{m|Splash}} via Metronome.}}\n\n{{TrainerPok\u00e9\n|trainer=Whitney\n|pkmn=Nidorina\n|gender=female\n|type1=Poison\n|img=Whitney Nidorina.png\n|epnum=EP158\n|epname=A Goldenrod Opportunity\n|vajp=Satomi Koorogi\n|vaen=Satomi Koorogi\n|desc={{p|Nidorina}} was the first Pok\u00e9mon used by Whitney in the [[Gym]] {{pkmn|battle}}, battling against {{AP|Cyndaquil}}. However, none of her attacks were a match for Cyndaquil's {{m|Flamethrower}}. Nidorina was soon defeated by Cyndaquil's second Flamethrower.\n\nNidorina's known moves are {{m|Poison Sting}} and {{m|Tackle}}.}}\n\n{{TrainerPok\u00e9\n|main=yes\n|trainer=Whitney\n|gender=female\n|pkmn=Miltank\n|type1=Normal\n|img=Whitney Miltank.png\n|epnum=EP158\n|epname=A Goldenrod Opportunity\n|vajp=Megumi Hayashibara\n|vaen=Megumi Hayashibara\n|desc=Whitney's {{p|Miltank}} was the last Pok\u00e9mon used in the [[Gym]] {{pkmn|battle}}. She managed to defeat {{AP|Cyndaquil}} by using {{m|Rollout}} continuously. {{Ash}} used {{AP|Totodile}}, telling him to use {{m|Water Gun}}; however, he did not slow Miltank down. With another Rollout, Totodile was knocked out. {{AP|Pikachu}} used {{m|Thunderbolt}} on Miltank, but it was ineffective. Pikachu was defeated by the second turn of Rollout.\n\nShe appeared again in the [[EP159|next episode]], sending {{TRT}} flying. In a friendly battle before Ash could challenge Whitney once again, she managed to defeat Ash's Cyndaquil and Totodile but was defeated by Ash's Pikachu, earning Ash the {{Badge|Plain}}.}}"}}}